assumpdoc/__init__.py
assumpdoc-0.0.1.dist-info/LICENSE
assumpdoc-0.0.1.dist-info/METADATA
assumpdoc-0.0.1.dist-info/WHEEL
assumpdoc-0.0.1.dist-info/top_level.txt
assumpdoc-0.0.1.dist-info/RECORD
